heatclient/__init__.py
heatclient/_i18n.py
heatclient/client.py
heatclient/exc.py
heatclient/shell.py
heatclient/common/__init__.py
heatclient/common/base.py
heatclient/common/deployment_utils.py
heatclient/common/environment_format.py
heatclient/common/event_utils.py
heatclient/common/format_utils.py
heatclient/common/hook_utils.py
heatclient/common/http.py
heatclient/common/resource_formatter.py
heatclient/common/template_format.py
heatclient/common/template_utils.py
heatclient/common/utils.py
heatclient/osc/__init__.py
heatclient/osc/plugin.py
heatclient/osc/v1/__init__.py
heatclient/osc/v1/build_info.py
heatclient/osc/v1/common.py
heatclient/osc/v1/event.py
heatclient/osc/v1/resource.py
heatclient/osc/v1/resource_type.py
heatclient/osc/v1/service.py
heatclient/osc/v1/snapshot.py
heatclient/osc/v1/software_config.py
heatclient/osc/v1/software_deployment.py
heatclient/osc/v1/stack.py
heatclient/osc/v1/stack_failures.py
heatclient/osc/v1/template.py
heatclient/tests/__init__.py
heatclient/tests/inline_templates.py
heatclient/tests/functional/__init__.py
heatclient/tests/functional/base.py
heatclient/tests/functional/config.py
heatclient/tests/functional/test_readonly_heat.py
heatclient/tests/functional/osc/__init__.py
heatclient/tests/functional/osc/v1/__init__.py
heatclient/tests/functional/osc/v1/base.py
heatclient/tests/functional/osc/v1/test_readonly.py
heatclient/tests/functional/osc/v1/test_stack.py
heatclient/tests/functional/templates/heat_minimal.yaml
heatclient/tests/functional/templates/heat_minimal_hot.yaml
heatclient/tests/test_templates/adopt.json
heatclient/tests/test_templates/adopt_with_file.json
heatclient/tests/test_templates/empty.yaml
heatclient/tests/test_templates/parameters.yaml
heatclient/tests/unit/__init__.py
heatclient/tests/unit/fakes.py
heatclient/tests/unit/test_actions.py
heatclient/tests/unit/test_build_info.py
heatclient/tests/unit/test_common_http.py
heatclient/tests/unit/test_deployment_utils.py
python_heatclient-5.0.0.dist-info/licenses/AUTHORS
python_heatclient-5.0.0.dist-info/licenses/LICENSE
python_heatclient-5.0.0.dist-info/METADATA
python_heatclient-5.0.0.dist-info/WHEEL
python_heatclient-5.0.0.dist-info/entry_points.txt
python_heatclient-5.0.0.dist-info/pbr.json
python_heatclient-5.0.0.dist-info/top_level.txt
python_heatclient-5.0.0.dist-info/RECORD
