Metadata-Version: 2.4
Name: python-heatclient
Version: 5.0.0
Summary: OpenStack Orchestration API Client Library
Home-page: https://docs.openstack.org/python-heatclient/latest
Author: OpenStack
Author-email: openstack-discuss@lists.openstack.org
Classifier: Development Status :: 5 - Production/Stable
Classifier: Environment :: Console
Classifier: Environment :: OpenStack
Classifier: Intended Audience :: Information Technology
Classifier: Intended Audience :: System Administrators
Classifier: License :: OSI Approved :: Apache Software License
Classifier: Operating System :: POSIX :: Linux
Classifier: Programming Language :: Python
Classifier: Programming Language :: Python :: 3
Classifier: Programming Language :: Python :: 3.10
Classifier: Programming Language :: Python :: 3.11
Classifier: Programming Language :: Python :: 3.12
Classifier: Programming Language :: Python :: 3 :: Only
Classifier: Programming Language :: Python :: Implementation :: CPython
Requires-Python: >=3.10
License-File: LICENSE
Requires-Dist: pbr>=2.0.0
Requires-Dist: cliff>=2.8.0
Requires-Dist: iso8601>=0.1.11
Requires-Dist: osc-lib>=1.14.0
Requires-Dist: PrettyTable>=0.7.2
Requires-Dist: oslo.i18n>=3.15.3
Requires-Dist: oslo.serialization>=2.18.0
Requires-Dist: oslo.utils>=3.33.0
Requires-Dist: keystoneauth1>=3.8.0
Requires-Dist: python-swiftclient>=3.2.0
Requires-Dist: PyYAML>=3.13
Requires-Dist: requests>=2.14.2
Dynamic: author
Dynamic: author-email
Dynamic: classifier
Dynamic: description
Dynamic: home-page
Dynamic: license-file
Dynamic: requires-dist
Dynamic: requires-python
Dynamic: summary
